bin/zlib.dll
exifmwg/__init__.py
exifmwg/bindings.cp310-win_amd64.pyd
exifmwg/bindings.cpp
exifmwg/bindings.pyi
exifmwg/DimensionsStruct.cpp
exifmwg/DimensionsStruct.hpp
exifmwg/Errors.hpp
exifmwg/ImageMetadata.cpp
exifmwg/ImageMetadata.hpp
exifmwg/KeywordInfoModel.cpp
exifmwg/KeywordInfoModel.hpp
exifmwg/Logging.hpp
exifmwg/MetadataKeys.hpp
exifmwg/Orientation.hpp
exifmwg/py.typed
exifmwg/PythonBindable.hpp
exifmwg/RegionInfoStruct.cpp
exifmwg/RegionInfoStruct.hpp
exifmwg/XmpAreaStruct.cpp
exifmwg/XmpAreaStruct.hpp
exifmwg/XmpSerializable.hpp
exifmwg/XmpUtils.cpp
exifmwg/XmpUtils.hpp
include/exiv2/basicio.hpp
include/exiv2/bmffimage.hpp
include/exiv2/bmpimage.hpp
include/exiv2/config.h
include/exiv2/convert.hpp
include/exiv2/cr2image.hpp
include/exiv2/crwimage.hpp
include/exiv2/datasets.hpp
include/exiv2/easyaccess.hpp
include/exiv2/epsimage.hpp
include/exiv2/error.hpp
include/exiv2/exif.hpp
include/exiv2/exiv2.hpp
include/exiv2/exiv2lib_export.h
include/exiv2/exv_conf.h
include/exiv2/futils.hpp
include/exiv2/gifimage.hpp
include/exiv2/image.hpp
include/exiv2/image_types.hpp
include/exiv2/iptc.hpp
include/exiv2/jp2image.hpp
include/exiv2/jpgimage.hpp
include/exiv2/metadatum.hpp
include/exiv2/mrwimage.hpp
include/exiv2/orfimage.hpp
include/exiv2/pgfimage.hpp
include/exiv2/photoshop.hpp
include/exiv2/preview.hpp
include/exiv2/properties.hpp
include/exiv2/psdimage.hpp
include/exiv2/rafimage.hpp
include/exiv2/rw2image.hpp
include/exiv2/slice.hpp
include/exiv2/tags.hpp
include/exiv2/tgaimage.hpp
include/exiv2/tiffimage.hpp
include/exiv2/types.hpp
include/exiv2/value.hpp
include/exiv2/version.hpp
include/exiv2/webpimage.hpp
include/exiv2/xmp_exiv2.hpp
include/exiv2/xmpsidecar.hpp
include/expat.h
include/expat_config.h
include/expat_external.h
include/zconf.h
include/zlib.h
lib/cmake/exiv2/exiv2Config.cmake
lib/cmake/exiv2/exiv2ConfigVersion.cmake
lib/cmake/expat-2.7.3/expat-config-version.cmake
lib/cmake/expat-2.7.3/expat-config.cmake
exifmwg-0.6.0.dist-info/METADATA
exifmwg-0.6.0.dist-info/WHEEL
exifmwg-0.6.0.dist-info/licenses/LICENSE
exifmwg-0.6.0.dist-info/RECORD
