Metadata-Version: 2.4
Name: exifmwg
Version: 0.6.0
Summary: A Python interface to read and write Metadata Working Group fields using exiftool
Keywords: exif,image,metadata,photo,photography
Author-Email: Trenton H <rda0128ou@mozmail.com>
License-Expression: MPL-2.0
Classifier: Development Status :: 4 - Beta
Classifier: Intended Audience :: Developers
Classifier: Operating System :: OS Independent
Classifier: Programming Language :: Python
Classifier: Programming Language :: Python :: 3 :: Only
Classifier: Programming Language :: Python :: 3.9
Classifier: Programming Language :: Python :: 3.10
Classifier: Programming Language :: Python :: 3.11
Classifier: Programming Language :: Python :: 3.12
Classifier: Programming Language :: Python :: 3.13
Classifier: Programming Language :: Python :: 3.14
Classifier: Programming Language :: Python :: Implementation :: CPython
Project-URL: Changelog, https://github.com/stumpylog/exifmwg/blob/main/CHANGELOG.md
Project-URL: Documentation, https://github.com/stumpylog/exifmwg/blob/main/README.md
Project-URL: Issues, https://github.com/stumpylog/exifmwg/issues
Project-URL: Source, https://github.com/stumpylog/exifmwg/
Requires-Python: >=3.9
